logsnag/__init__.py
logsnag/constants.py
logsnag/exceptions.py
logsnag/logsnag.py
logsnag/utils.py
logsnag/version.py
logsnag-1.0.1.dist-info/LICENSE
logsnag-1.0.1.dist-info/METADATA
logsnag-1.0.1.dist-info/WHEEL
logsnag-1.0.1.dist-info/top_level.txt
logsnag-1.0.1.dist-info/RECORD
