Metadata-Version: 2.1
Name: logsnag
Version: 1.0.1
Summary: LogSnag API Wrapper
Home-page: https://github.com/logsnag/logsnag.py
Author: Shayan Taslim
Author-email: shayan@logsnag.com
License: MIT
Project-URL: Homepage, https://logsnag.com
Project-URL: Documentation, https://docs.logsnag.com
Project-URL: Playground, https://logsnag.com/playground
Project-URL: Github, https://github.com/LogSnag/logsnag.py
Platform: UNKNOWN
Classifier: Programming Language :: Python
Classifier: Programming Language :: Python :: 3
Classifier: Programming Language :: Python :: 3.6
Classifier: Programming Language :: Python :: 3.7
Classifier: Programming Language :: Python :: 3.8
Requires-Python: >=3.6
License-File: LICENSE
Requires-Dist: requests
